odoo/addons/document_quick_access_folder_auto_classification/README.rst
odoo/addons/document_quick_access_folder_auto_classification/__init__.py
odoo/addons/document_quick_access_folder_auto_classification/__manifest__.py
odoo/addons/document_quick_access_folder_auto_classification/data/config_parameter.xml
odoo/addons/document_quick_access_folder_auto_classification/data/cron_data.xml
odoo/addons/document_quick_access_folder_auto_classification/i18n/document_quick_access_folder_auto_classification.pot
odoo/addons/document_quick_access_folder_auto_classification/models/__init__.py
odoo/addons/document_quick_access_folder_auto_classification/models/document_quick_access_missing.py
odoo/addons/document_quick_access_folder_auto_classification/models/document_quick_access_rule.py
odoo/addons/document_quick_access_folder_auto_classification/models/ir_attachment.py
odoo/addons/document_quick_access_folder_auto_classification/readme/CONFIGURE.rst
odoo/addons/document_quick_access_folder_auto_classification/readme/CONTRIBUTORS.rst
odoo/addons/document_quick_access_folder_auto_classification/readme/DESCRIPTION.rst
odoo/addons/document_quick_access_folder_auto_classification/readme/USAGE.rst
odoo/addons/document_quick_access_folder_auto_classification/security/ir.model.access.csv
odoo/addons/document_quick_access_folder_auto_classification/security/security.xml
odoo/addons/document_quick_access_folder_auto_classification/static/description/icon.png
odoo/addons/document_quick_access_folder_auto_classification/static/description/icon.svg
odoo/addons/document_quick_access_folder_auto_classification/static/description/index.html
odoo/addons/document_quick_access_folder_auto_classification/tests/__init__.py
odoo/addons/document_quick_access_folder_auto_classification/tests/test_document_quick_access_auto_classification.py
odoo/addons/document_quick_access_folder_auto_classification/tests/test_file.pdf
odoo11_addon_document_quick_access_folder_auto_classification-11.0.1.0.1.dist-info/METADATA
odoo11_addon_document_quick_access_folder_auto_classification-11.0.1.0.1.dist-info/WHEEL
odoo11_addon_document_quick_access_folder_auto_classification-11.0.1.0.1.dist-info/top_level.txt
odoo11_addon_document_quick_access_folder_auto_classification-11.0.1.0.1.dist-info/RECORD
