Metadata-Version: 2.1
Name: odoo11-addon-document-quick-access-folder-auto-classification
Version: 11.0.1.0.1
Summary: Auto classification of Documents after reading a QR
Home-page: https://github.com/OCA/server-ux
Author: Creu Blanca,Odoo Community Association (OCA)
Author-email: support@odoo-community.org
License: AGPL-3
Platform: UNKNOWN
Classifier: Programming Language :: Python
Classifier: Framework :: Odoo
Classifier: License :: OSI Approved :: GNU Affero General Public License v3
Requires-Python: >=2.7, !=3.0.*, !=3.1.*, !=3.2.*, !=3.3.*, !=3.4.*
Requires-Dist: odoo11-addon-document-quick-access
Requires-Dist: odoo11-addon-queue-job
Requires-Dist: odoo (<11.1dev,>=11.0a)
Requires-Dist: pdf2image
Requires-Dist: pyzbar
